graph_of_words.py
graph_of_words-0.1.dist-info/METADATA
graph_of_words-0.1.dist-info/WHEEL
graph_of_words-0.1.dist-info/top_level.txt
graph_of_words-0.1.dist-info/RECORD
