Metadata-Version: 2.1
Name: graph-of-words
Version: 0.1
Summary: A module to generate a graph of words
Home-page: https://pypi.org/project/graph-of-words/
Author: Vincent Lequertier
Author-email: vi.le@autistici.org
License: UNKNOWN
Project-URL: Bug Reports, https://gitlab.com/vi.le/graphofwords/-/issues
Project-URL: Documentation, http://vi.le.gitlab.io/graphofwords/
Project-URL: Source, https://gitlab.com/vi.le/graphofwords
Keywords: networkx graph words nlp
Platform: UNKNOWN
Classifier: Development Status :: 3 - Alpha
Classifier: Intended Audience :: Developers
Classifier: Topic :: Scientific/Engineering :: Artificial Intelligence
Classifier: License :: OSI Approved :: GNU General Public License v3 (GPLv3)
Classifier: Programming Language :: Python :: 3
Classifier: Programming Language :: Python :: 3.5
Classifier: Programming Language :: Python :: 3.6
Classifier: Programming Language :: Python :: 3.7
Classifier: Programming Language :: Python :: 3.8
Requires-Python: >=3.5, <4
Requires-Dist: networkx
